lyrik/__init__.py
lyrik/__main__.py
lyrik/src/adaptor.py
lyrik/src/dbus_adaptor.py
lyrik/src/interface_manager.py
lyrik/src/lyrickrc.toml
lyrik/src/main.py
lyrik/src/main_application.py
lyrik/src/mpris_watcher.py
lyrik/src/netease_music_interface.py
lyrik/src/netwrok_interface.py
lyrik-0.1.0.dist-info/LICENSE
lyrik-0.1.0.dist-info/METADATA
lyrik-0.1.0.dist-info/WHEEL
lyrik-0.1.0.dist-info/RECORD
