Metadata-Version: 2.1
Name: lyrik
Version: 0.1.0
Summary: Provide lyrics service through D-Bus.
Home-page: https://github.com/LiYulin-s/LyriK
License: GPLv3
Keywords: lyrics,dbus
Author: Lee_Yurin
Author-email: liyulin.self@foxmail.com
Requires-Python: >=3.10,<4.0
Classifier: License :: Other/Proprietary License
Classifier: Programming Language :: Python :: 3
Classifier: Programming Language :: Python :: 3.10
Classifier: Programming Language :: Python :: 3.11
Requires-Dist: dbus-next (>=0.2.3,<0.3.0)
Requires-Dist: loguru (>=0.7.0,<0.8.0)
Requires-Dist: pycloudmusic (>=0.1.4.5,<0.2.0.0)
